get_conn_by_id/__init__.py
get_conn_by_id/__version__.py
get_conn_by_id/get_conn_by_id_airflow/__init__.py
get_conn_by_id/get_conn_by_id_json/__init__.py
get_conn_by_id/get_conn_by_id_json/get_credential_url/__init__.py
get_conn_by_id/get_conn_by_id_json/get_credential_url/databricks/__init__.py
get_conn_by_id/get_conn_by_id_json/get_credential_url/local/__init__.py
get_conn_by_id/get_conn_by_id_synapse/__init__.py
get_conn_by_id/get_conn_by_id_synapse/connect_lake_and_fetch_json/__init__.py
get_conn_by_id/get_conn_by_id_synapse/datalake/__init__.py
get_conn_by_id-0.0.6.dist-info/licenses/LICENSE
get_conn_by_id-0.0.6.dist-info/METADATA
get_conn_by_id-0.0.6.dist-info/WHEEL
get_conn_by_id-0.0.6.dist-info/top_level.txt
get_conn_by_id-0.0.6.dist-info/RECORD
