Metadata-Version: 2.4
Name: get_conn_by_id
Version: 0.0.6
Summary: A library used to get the connections from different environments.
Author-email: Cody Xiaozhan Yang <x.yang@cloudfmgroup.com>
License: MIT License
Keywords: connections
Classifier: Programming Language :: Python :: 3
Classifier: License :: OSI Approved :: MIT License
Classifier: Operating System :: OS Independent
Requires-Python: >=3.8
License-File: LICENSE
Dynamic: license-file
